drf_totp/__init__.py
drf_totp/admin.py
drf_totp/apps.py
drf_totp/models.py
drf_totp/serializers.py
drf_totp/tests.py
drf_totp/urls.py
drf_totp/views.py
drf_totp/migrations/0001_initial.py
drf_totp/migrations/__init__.py
drf_totp-0.1.4.dist-info/METADATA
drf_totp-0.1.4.dist-info/WHEEL
drf_totp-0.1.4.dist-info/licenses/LICENSE
drf_totp-0.1.4.dist-info/RECORD
