Metadata-Version: 2.3
Name: drf-totp
Version: 0.1.4
Summary: TOTP (Time-based One-Time Password) authentication for Django REST Framework
Project-URL: Homepage, https://github.com/mohamed-alired/drf-totp
Project-URL: Repository, https://github.com/mohamed-alired/drf-totp.git
Project-URL: Issues, https://github.com/mohamed-alired/drf-totp/issues
Author-email: djv-mo <solutiond700@gmail.com>
License: MIT
Keywords: 2fa,authentication,django,framework,mfa,rest,totp
Classifier: Development Status :: 3 - Alpha
Classifier: Environment :: Web Environment
Classifier: Framework :: Django
Classifier: Framework :: Django :: 4.2
Classifier: Intended Audience :: Developers
Classifier: License :: OSI Approved :: MIT License
Classifier: Operating System :: OS Independent
Classifier: Programming Language :: Python
Classifier: Programming Language :: Python :: 3
Classifier: Programming Language :: Python :: 3.8
Classifier: Programming Language :: Python :: 3.9
Classifier: Programming Language :: Python :: 3.10
Classifier: Programming Language :: Python :: 3.11
Classifier: Topic :: Internet :: WWW/HTTP
Classifier: Topic :: Security
Classifier: Topic :: Software Development :: Libraries :: Python Modules
Requires-Python: >=3.8
Requires-Dist: django>=4.2
Requires-Dist: djangorestframework>=3.14.0
Requires-Dist: pyotp>=2.8.0
